toyhouse/__init__.py
toyhouse/character.py
toyhouse/forum.py
toyhouse/session.py
toyhouse/user.py
toyhouse/utilities.py
toyhouse-0.2.2.dist-info/licenses/LICENSE
toyhouse-0.2.2.dist-info/METADATA
toyhouse-0.2.2.dist-info/WHEEL
toyhouse-0.2.2.dist-info/top_level.txt
toyhouse-0.2.2.dist-info/RECORD
