Metadata-Version: 2.4
Name: toyhouse
Version: 0.2.2
Summary: An unofficial Python API for the site Toyhou.se
Author-email: Annabel Quach <annabelquach13@gmail.com>
Project-URL: Homepage, https://github.com/phthallo/toyhouse-data
Project-URL: Bug Tracker, https://github.com/phthallo/toyhouse-data/issues
Classifier: Programming Language :: Python :: 3
Classifier: License :: OSI Approved :: GNU General Public License v3 (GPLv3)
Classifier: Operating System :: OS Independent
Classifier: Development Status :: 2 - Pre-Alpha
Requires-Python: >=3.8
License-File: LICENSE
Requires-Dist: beautifulsoup4>=4.12.2
Requires-Dist: lxml>=4.5.0
Requires-Dist: requests>=2.31.0
Dynamic: license-file
